openbb_cookiecutter/__init__.py
openbb_cookiecutter/cli.py
openbb_cookiecutter/template/cookiecutter.json
openbb_cookiecutter/template/hooks/post_gen_project.py
openbb_cookiecutter/template/hooks/pre_gen_project.py
openbb_cookiecutter/template/{{cookiecutter.project_tag}}/.coveragerc
openbb_cookiecutter/template/{{cookiecutter.project_tag}}/.gitignore
openbb_cookiecutter/template/{{cookiecutter.project_tag}}/.secrets.baseline
openbb_cookiecutter/template/{{cookiecutter.project_tag}}/README.md
openbb_cookiecutter/template/{{cookiecutter.project_tag}}/pyproject.toml
openbb_cookiecutter/template/{{cookiecutter.project_tag}}/pytest.ini
openbb_cookiecutter/template/{{cookiecutter.project_tag}}/ruff.toml
openbb_cookiecutter/template/{{cookiecutter.project_tag}}/tests/.gitkeep
openbb_cookiecutter/template/{{cookiecutter.project_tag}}/tests/conftest.py
openbb_cookiecutter/template/{{cookiecutter.project_tag}}/{{cookiecutter.package_name}}/obbject/__init__.py
openbb_cookiecutter/template/{{cookiecutter.project_tag}}/{{cookiecutter.package_name}}/obbject/{{cookiecutter.obbject_name}}/__init__.py
openbb_cookiecutter/template/{{cookiecutter.project_tag}}/{{cookiecutter.package_name}}/providers/__init__.py
openbb_cookiecutter/template/{{cookiecutter.project_tag}}/{{cookiecutter.package_name}}/providers/{{cookiecutter.provider_name}}/__init__.py
openbb_cookiecutter/template/{{cookiecutter.project_tag}}/{{cookiecutter.package_name}}/providers/{{cookiecutter.provider_name}}/models/__init__.py
openbb_cookiecutter/template/{{cookiecutter.project_tag}}/{{cookiecutter.package_name}}/providers/{{cookiecutter.provider_name}}/models/example.py
openbb_cookiecutter/template/{{cookiecutter.project_tag}}/{{cookiecutter.package_name}}/providers/{{cookiecutter.provider_name}}/models/ohlc_example.py
openbb_cookiecutter/template/{{cookiecutter.project_tag}}/{{cookiecutter.package_name}}/providers/{{cookiecutter.provider_name}}/utils/__init__.py
openbb_cookiecutter-0.4.0.dist-info/METADATA
openbb_cookiecutter-0.4.0.dist-info/WHEEL
openbb_cookiecutter-0.4.0.dist-info/entry_points.txt
openbb_cookiecutter-0.4.0.dist-info/RECORD
