Metadata-Version: 2.4
Name: openbb-cookiecutter
Version: 0.4.0
Summary: Extensions template for the OpenBB Python Package.
License: AGPL-3.0-only
Author: OpenBB Team
Author-email: hello@openbb.co
Requires-Python: >=3.10,<3.14
Classifier: License :: OSI Approved :: GNU Affero General Public License v3
Classifier: Programming Language :: Python :: 3
Classifier: Programming Language :: Python :: 3.10
Classifier: Programming Language :: Python :: 3.11
Classifier: Programming Language :: Python :: 3.12
Classifier: Programming Language :: Python :: 3.13
Requires-Dist: cookiecutter (>=2.6.0,<3.0.0)
Project-URL: Homepage, https://openbb.co
Project-URL: Repository, https://github.com/OpenBB-finance/openbb-cookiecutter
